_libbatch.so
libbatch.py
libbatch.libs/libbatch-2b3173ba.so
libbatch-2.5.0.dist-info/METADATA
libbatch-2.5.0.dist-info/WHEEL
libbatch-2.5.0.dist-info/RECORD
